{
  "lastUpdated": "2026-05-10T22:47:06.038Z",
  "sampleSize": 5522,
  "severityDistribution": {
    "Critical": 505,
    "High": 1923,
    "Medium": 2085,
    "Low": 269,
    "Unknown": 740
  },
  "topTechnologies": [
    {
      "name": "Linux kernel",
      "count": 437
    },
    {
      "name": "Chrome",
      "count": 191
    },
    {
      "name": "Openclaw",
      "count": 156
    },
    {
      "name": "Windows 10 1607",
      "count": 76
    },
    {
      "name": "Firefox",
      "count": 47
    },
    {
      "name": "Coreutils",
      "count": 44
    },
    {
      "name": "Wireshark",
      "count": 43
    },
    {
      "name": "Mysql server",
      "count": 25
    }
  ]
}