{
  "lastUpdated": "2026-05-17T20:51:08.200Z",
  "sampleSize": 6252,
  "severityDistribution": {
    "Critical": 572,
    "High": 2245,
    "Medium": 2533,
    "Low": 267,
    "Unknown": 635
  },
  "topTechnologies": [
    {
      "name": "Linux kernel",
      "count": 698
    },
    {
      "name": "Openclaw",
      "count": 170
    },
    {
      "name": "Chrome",
      "count": 161
    },
    {
      "name": "Ipados",
      "count": 71
    },
    {
      "name": "Firefox",
      "count": 56
    },
    {
      "name": "Coreutils",
      "count": 44
    },
    {
      "name": "Wireshark",
      "count": 43
    },
    {
      "name": "Windows 10 1607",
      "count": 43
    }
  ]
}