{
  "lastUpdated": "2026-05-12T10:31:24.498Z",
  "sampleSize": 5917,
  "severityDistribution": {
    "Critical": 529,
    "High": 2045,
    "Medium": 2290,
    "Low": 281,
    "Unknown": 772
  },
  "topTechnologies": [
    {
      "name": "Linux kernel",
      "count": 520
    },
    {
      "name": "Chrome",
      "count": 191
    },
    {
      "name": "Openclaw",
      "count": 153
    },
    {
      "name": "Windows 10 1607",
      "count": 76
    },
    {
      "name": "Firefox",
      "count": 51
    },
    {
      "name": "Coreutils",
      "count": 44
    },
    {
      "name": "Wireshark",
      "count": 43
    },
    {
      "name": "Mysql server",
      "count": 25
    }
  ]
}